pdf_to_book/__init__.py
pdf_to_book/__main__.py
pdf_to_book/pdf_to_book.py
pdf_to_book-0.0.3.dist-info/licenses/LICENSE
pdf_to_book-0.0.3.dist-info/METADATA
pdf_to_book-0.0.3.dist-info/WHEEL
pdf_to_book-0.0.3.dist-info/entry_points.txt
pdf_to_book-0.0.3.dist-info/top_level.txt
pdf_to_book-0.0.3.dist-info/RECORD
