Metadata-Version: 2.4
Name: pdf_to_book
Version: 0.0.3
Summary: Lightweight Python package for converting a pdf into a print-ready book format.
Author-email: Jesse Canavan <canav021@umn.edu>
License-Expression: MIT
Project-URL: Homepage, https://github.com/JesseCan9000/pdf-to-book
Project-URL: Issues, https://github.com/JesseCan9000/pdf-to-book/issues
Classifier: Programming Language :: Python :: 3
Classifier: Operating System :: OS Independent
Requires-Python: >=3.8
License-File: LICENSE
Requires-Dist: pymupdf
Dynamic: license-file
